{
 "ok": {
  "mistral": 12
 },
 "err": {
  "gemini:429": 12
 },
 "ro_reject": {
  "mistral": 2
 },
 "samples": [
  {
   "p": "mistral",
   "raw": "{\"titlu\":\"Tensiuni SUA-Iran amenință să readucă prețul benzinei peste 4 dolari pe galon în America\",\"fapt\":\"Statele Unite și Iranul se confruntă pentru controlul Strâmtorii Hormuz, punând presiune pe "
  },
  {
   "p": "mistral",
   "raw": "{\"titlu\":\"Băncile americane înregistrează recorduri la tranzacționarea de acțiuni, datorită exploziei pieței\", \"fapt\":\"Volumele de tranzacționare la bursă pe Wall Street au atins niveluri istorice, în"
  },
  {
   "p": "mistral",
   "raw": "{\"titlu\":\"Băncile americane de top, câștigătoarele ascunse ale revoluției AI\", \"fapt\":\"Goldman Sachs și JPMorgan au raportat venituri record în ultimul trimestru, susținute de creșterea puternică a ac"
  },
  {
   "p": "mistral",
   "raw": "{\"titlu\":\"Posibilă creștere a prețului iPhone-ului 18 ar putea susține acțiunile Apple\", \"fapt\":\"Analistii de la Morgan Stanley anticipează o majorare de până la 200 de dolari pentru noua generație de"
  },
  {
   "p": "mistral",
   "raw": "```json\n{\"titlu\":\"Angajații IBM pierd 400 de milioane de dolari din cauza plasamentelor în acțiuni proprii\", \"fapt\":\"Angajații IBM care au investit în acțiuni ale companiei au suportat pierderi totale"
  },
  {
   "p": "mistral",
   "raw": "```json\n{\"titlu\":\"Câștigurile companiilor, inflația și tensiunile cu Iranul influențează piețele globale\",\"fapt\":\"Trei factori cheie — rezultatele financiare ale firmelor, presiunea inflaționistă și e"
  }
 ],
 "no_keys": [],
 "summary": {
  "new": 10,
  "fresh": 10,
  "fb": 0,
  "tier2": 0,
  "explainer": 10
 }
}