{
 "ok": {
  "mistral": 11
 },
 "err": {
  "gemini:429": 13
 },
 "ro_reject": {
  "mistral": 6
 },
 "samples": [
  {
   "p": "mistral",
   "raw": "```json\n{\"titlu\":\"Rezerva Federală ar putea anula reducerile de dobândă din 2025 sau să le mențină la zero, avertizează experții\",\"fapt\":\"RBC Wealth Management estimează că Rezerva Federală (Fed) va r"
  },
  {
   "p": "mistral",
   "raw": "```json\n{\"titlu\":\"Reîntoarcerea profitabilă a unei strategii riscante pe piața valutară, potrivit Goldman Sachs\",\"fapt\":\"Un fond de acoperire a pierderilor (hedge fund) asociat cu un colaps major din "
  },
  {
   "p": "mistral",
   "raw": "```json\n{\"titlu\":\"Operațiunea de „carry trade” în valută revine puternic, avertizează Goldman Sachs\", \"fapt\":\"Piața financiară asistă la o reluare a strategiei de „carry trade” în valută, care a cauza"
  },
  {
   "p": "mistral",
   "raw": "```json\n{\"titlu\":\"Carry trade pe piețele valutare revine puternic, avertizează Goldman Sachs\",\"fapt\":\"Piața valutară a văzut o revenire a strategiei de tip carry trade, una dintre cele mai riscante op"
  },
  {
   "p": "mistral",
   "raw": "{\"titlu\":\"O tranzacție a unui fond de hedging, responsabilă pentru un colaps masiv al pieței în 2024, a revenit în forță, susține Goldman Sachs\",\"fapt\":\"Tranzacția de tip *carry trade* pe piața valuta"
  },
  {
   "p": "mistral",
   "raw": "{\"titlu\":\"O tranzacție a unui fond de hedge care a provocat un colaps masiv pe piață în 2024 a revenit puternic, susține Goldman Sachs\",\"fapt\":\"Revenirea tranzacției de tip *carry trade* pe piața valu"
  }
 ],
 "no_keys": [],
 "summary": {
  "new": 8,
  "fresh": 8,
  "fb": 0,
  "tier2": 0,
  "explainer": 8
 }
}