{
 "ok": {
  "mistral": 7
 },
 "err": {
  "gemini:429": 7
 },
 "ro_reject": {
  "mistral": 1
 },
 "samples": [
  {
   "p": "mistral",
   "raw": "{\"titlu\":\"Analiștii BofA recomandă investitoriilor să cumpere acțiuni cu potențial de creștere rapidă, vizând un avans de 5%\",\"fapt\":\"Specialiștii în tranzacționare din cadrul BofA consideră că acțiun"
  },
  {
   "p": "mistral",
   "raw": "```json\n{\"titlu\":\"Analiștii BofA recomandă cumpărarea acțiunilor cu creștere rapidă, vizând un avans de 5%\", \"fapt\":\"Banca de investiții BofA sugerează investitorilor să achiziționeze acțiuni ale comp"
  },
  {
   "p": "mistral",
   "raw": "{\"titlu\":\"Paulson avertizează: piața aurului intră într-un ciclu lung de creștere\", \"fapt\":\"Investitorul John Paulson susține că cererea globală de aur se extinde, fiind susținută atât de băncile cent"
  },
  {
   "p": "mistral",
   "raw": "```json\n{\"titlu\":\"Economia gig din China: ce se întâmplă și ce înseamnă pentru piața muncii și economiile globale\",\"fapt\":\"China analizează impactul economiei gig asupra angajaților și companiilor, pr"
  },
  {
   "p": "mistral",
   "raw": "```json\n{\"titlu\":\"De ce au scăzut acțiunile PSKY, McDonald’s și Northrop Grumman la minimele anului?\", \"fapt\":\"Acțiunile a trei mari companii americane — PSKY (companie de plăți), McDonald’s (lanț de "
  },
  {
   "p": "mistral",
   "raw": "{\"titlu\":\"Război în Iran: cum ar putea afecta economia globală și buzunarele românilor\", \"fapt\":\"Dezbaterile din presa americană avertizează că un conflict militar cu Iranul ar putea declanșa o criză "
  }
 ],
 "no_keys": [],
 "summary": {
  "new": 5,
  "fresh": 5,
  "fb": 0,
  "tier2": 0,
  "explainer": 5
 }
}