{
 "ok": {
  "mistral": 4
 },
 "err": {
  "gemini:429": 4
 },
 "ro_reject": {},
 "samples": [
  {
   "p": "mistral",
   "raw": "{\"titlu\":\"Zeci de traderi americani se îndreaptă către cel mai riscant produs din cripto\", \"fapt\":\"Zeci de traderi din SUA au început să tranzacționeze masiv un produs cripto considerat extrem de vola"
  },
  {
   "p": "mistral",
   "raw": "{\"titlu\":\"Țițeiul iranian nu va afecta piața energetică americană, susține LS Power\",\"fapt\":\"LS Power declară că piața electricității din SUA este protejată de eventualele perturbări cauzate de sancți"
  },
  {
   "p": "mistral",
   "raw": "```json\n[]\n```"
  },
  {
   "p": "mistral",
   "raw": "```json\n[{\"i\":0,\"titlu\":\"Maleda Bisrat, Kefi Gold and Copper PLC: Profil și biografie - Bloomberg.com\",\"fapt\":\"Articolul prezintă profilul și biografia Maledei Bisrat în cadrul companiei Kefi Gold and"
  }
 ],
 "no_keys": [],
 "summary": {
  "new": 2,
  "fresh": 10,
  "fb": 0,
  "tier2": 0,
  "explainer": 10
 }
}