{
 "ok": {
  "mistral": 9
 },
 "err": {
  "gemini:429": 9
 },
 "ro_reject": {
  "mistral": 1
 },
 "samples": [
  {
   "p": "mistral",
   "raw": "{\"titlu\":\"Senatul american aprobă proiectul de lege împotriva mașinilor electrice din China\",\"fapt\":\"Comisia Senatului SUA a aprobat un proiect de lege care vizează restricționarea accesului vehiculel"
  },
  {
   "p": "mistral",
   "raw": "```json\n{\"titlu\":\"Senatul american avansează proiect de lege împotriva mașinilor electrice chinezești pe piața SUA\",\"fapt\":\"Comisia Senatului american a aprobat un proiect de lege care vizează restric"
  },
  {
   "p": "mistral",
   "raw": "```json\n{\"titlu\":\"Acțiuni care au înregistrat cele mai mari fluctuații în sesiunea de after-hours: Alphabet, Tesla, IBM, Las Vegas Sands și ServiceNow\", \"fapt\":\"În afara programului obișnuit de tranza"
  },
  {
   "p": "mistral",
   "raw": "```json\n{\"titlu\":\"Acțiuni cu cele mai mari variații în sesiunea de după închidere: Alphabet, Tesla, IBM, Las Vegas Sands și altele\",\"fapt\":\"În sesiunea de tranzacționare de după închidere, acțiunile u"
  },
  {
   "p": "mistral",
   "raw": "```json\n{\"titlu\":\"Instalările de panouri solare noi în China scad cu două treimi în prima jumătate a anului, din cauza reformei prețurilor\",\"fapt\":\"China a înregistrat o scădere de 66% a capacității n"
  },
  {
   "p": "mistral",
   "raw": "{\"titlu\":\"Tesla înregistrează venituri peste așteptări, dar profitul sub previziuni în al doilea trimestru\", \"fapt\":\"Tesla a raportat venituri mai mari decât estimările pentru T2 2024, dar profitul ne"
  }
 ],
 "no_keys": [],
 "summary": {
  "new": 7,
  "fresh": 7,
  "fb": 0,
  "tier2": 0,
  "explainer": 7
 }
}