{
 "ok": {
  "mistral": 3
 },
 "err": {
  "gemini:429": 3
 },
 "ro_reject": {},
 "samples": [
  {
   "p": "mistral",
   "raw": "{\"titlu\":\"Bursele londoneze vor funcționa non-stop din 2025, o premieră pentru Europa\", \"fapt\":\"London Stock Exchange va introduce tranzacționarea continuă 24/7 începând din anul viitor, prima bursă e"
  },
  {
   "p": "mistral",
   "raw": "```json\n[]\n```"
  },
  {
   "p": "mistral",
   "raw": "```json\n[\n  {\"i\":0,\"titlu\":\"Cum ar putea inteligența artificială să destabilizeze guvernele\",\"fapt\":\"Tehnologiile avansate de inteligență artificială ar putea slăbi stabilitatea politică prin manipula"
  }
 ],
 "no_keys": [],
 "summary": {
  "new": 1,
  "fresh": 15,
  "fb": 0,
  "tier2": 0,
  "explainer": 15
 }
}