{
 "ok": {
  "mistral": 6
 },
 "err": {
  "gemini:429": 6
 },
 "ro_reject": {},
 "samples": [
  {
   "p": "mistral",
   "raw": "{\"titlu\":\"Acțiunile din sectorul cipurilor intră în teritoriu de piață în scădere. Analistul BofA sfătuiește calmul\",\"fapt\":\"Sectorul semiconductorilor traversează o corecție, fiind predispus la perfo"
  },
  {
   "p": "mistral",
   "raw": "{\"titlu\":\"Acțiunile din sectorul cipurilor intră în teritoriu de piață urs.\", \"fapt\":\"Un analist de la Banca Americii recomandă să nu se panicheze în această situație.\"}"
  },
  {
   "p": "mistral",
   "raw": "```json\n{\"titlu\":\"Două acțiuni profitabile și una ignorată din lista noastră de achiziții\", \"fapt\":\"Un analist financiar recomandă două companii cu randamente solide, în timp ce ignoră o a treia din l"
  },
  {
   "p": "mistral",
   "raw": "```json\n[]\n```"
  },
  {
   "p": "mistral",
   "raw": "```json\n[\n  {\"i\":0,\"titlu\":\"Maleda Bisrat, Kefi Gold and Copper PLC: Profil și biografie - Bloomberg.com\",\"fapt\":\"Maleda Bisrat este un profil prezentat de Bloomberg în cadrul companiei Kefi Gold and "
  },
  {
   "p": "mistral",
   "raw": "[{\"i\":0,\"ce\":\"Scăderea acțiunilor din sectorul cipurilor afectează direct portofoliile românilor care investesc în ETF-uri globale sau fonduri de pensii private, deoarece aceste active sunt componente"
  }
 ],
 "no_keys": [],
 "summary": {
  "new": 2,
  "fresh": 2,
  "fb": 0,
  "tier2": 0,
  "explainer": 2
 }
}